githead/__init__.py
githead/py.typed
githead-1.2.1.dist-info/METADATA
githead-1.2.1.dist-info/WHEEL
githead-1.2.1.dist-info/licenses/LICENSE
githead-1.2.1.dist-info/RECORD
