Metadata-Version: 2.4
Name: githead
Version: 1.2.1
Summary: Simple utility for getting the current git commit hash (HEAD)
Project-URL: Issues, https://github.com/Zaczero/githead/issues
Project-URL: Repository, https://github.com/Zaczero/githead
Author-email: Kamil Monicz <kamil@monicz.dev>
License-File: LICENSE
Keywords: commit,git,git-commit,hash,head,vcs,version-control
Classifier: Development Status :: 5 - Production/Stable
Classifier: Intended Audience :: Developers
Classifier: License :: OSI Approved :: The Unlicense (Unlicense)
Classifier: Operating System :: OS Independent
Classifier: Programming Language :: Python :: 3.9
Classifier: Programming Language :: Python :: 3.10
Classifier: Programming Language :: Python :: 3.11
Classifier: Programming Language :: Python :: 3.12
Classifier: Programming Language :: Python :: 3.13
Classifier: Topic :: Software Development :: Libraries :: Python Modules
Classifier: Typing :: Typed
Requires-Python: >=3.9
